gradio_themer/__init__.py
gradio_themer/generate_theme_template.py
gradio_themer/gradio_themer.py
gradio_themer/gradio_themer.pyi
gradio_themer/templates/component/index.js
gradio_themer/templates/component/style.css
gradio_themer/templates/example/index.js
gradio_themer/templates/example/style.css
gradio_themer-0.1.0.dist-info/METADATA
gradio_themer-0.1.0.dist-info/WHEEL
gradio_themer-0.1.0.dist-info/RECORD
