Metadata-Version: 2.4
Name: gradio_themer
Version: 0.1.0
Summary: User-configurable themes for Gradio applications - unlimited custom themes via JSON configuration
Author-email: Eldar Syzdykov <eldar@utexas.edu>
License-Expression: MIT
Keywords: gradio-custom-component,gradio-styling,gradio-themes,ui-themes,user-configurable
Classifier: Development Status :: 3 - Alpha
Classifier: Operating System :: OS Independent
Classifier: Programming Language :: Python :: 3
Classifier: Programming Language :: Python :: 3 :: Only
Classifier: Programming Language :: Python :: 3.8
Classifier: Programming Language :: Python :: 3.9
Classifier: Programming Language :: Python :: 3.10
Classifier: Programming Language :: Python :: 3.11
Classifier: Topic :: Scientific/Engineering
Classifier: Topic :: Scientific/Engineering :: Artificial Intelligence
Classifier: Topic :: Scientific/Engineering :: Visualization
Requires-Python: >=3.8
Requires-Dist: gradio<6.0,>=4.0
Provides-Extra: dev
Requires-Dist: build; extra == 'dev'
Requires-Dist: twine; extra == 'dev'
